pyheapfile/__init__.py
pyheapfile/heap.py
pyheapfile/hexdump.py
pyheapfile-0.0.3.dist-info/LICENSE.md
pyheapfile-0.0.3.dist-info/METADATA
pyheapfile-0.0.3.dist-info/WHEEL
pyheapfile-0.0.3.dist-info/top_level.txt
pyheapfile-0.0.3.dist-info/RECORD
