Metadata-Version: 2.1
Name: pyheapfile
Version: 0.0.3
Summary: pyheapfile - python heap file storage memory management
Home-page: https://github.com/kr-g/pyheapfile
Author: k.r. goger
Author-email: k.r.goger+pyheapfile@gmail.com
License: UNKNOWN
Keywords: heap file storage memory management
Platform: UNKNOWN
Classifier: Development Status :: 3 - Alpha
Classifier: Operating System :: POSIX :: Linux
Classifier: Intended Audience :: Developers
Classifier: Programming Language :: Python :: 3
Classifier: License :: OSI Approved :: GNU Affero General Public License v3 or later (AGPLv3+)
Requires-Python: >=3.6
